{
    "entities": [
        {
            "children": null,
            "flip_axis": [
                1.0,
                1.0,
                1.0
            ],
            "group_id": 2,
            "name": "rocket",
            "position": [
                -55.0,
                33.0,
                -17.0
            ],
            "rotation": [
                1.0,
                0.0,
                0.0,
                0.0
            ],
            "scale": 80.0
        },
        {
            "children": null,
            "flip_axis": [
                1.0,
                1.0,
                1.0
            ],
            "group_id": 3,
            "name": "milou",
            "position": [
                -4.0,
                -0.12700000405311584,
                1.7999999523162842
            ],
            "rotation": [
                0.4580000042915344,
                0.0,
                -0.8889999985694885,
                0.0
            ],
            "scale": 0.6399999856948853
        },
        {
            "children": [
                {
                    "children": null,
                    "flip_axis": [
                        -1.0,
                        1.0,
                        1.0
                    ],
                    "group_id": 6,
                    "name": "right_leg",
                    "position": [
                        -0.1089860200881958,
                        -0.591317892074585,
                        -0.043814003467559814
                    ],
                    "rotation": [
                        0.9979902505874634,
                        0.040619052946567535,
                        -0.04862472414970398,
                        0.0012661628425121307
                    ],
                    "scale": 0.7149999737739563
                },
                {
                    "children": null,
                    "flip_axis": [
                        1.0,
                        1.0,
                        1.0
                    ],
                    "group_id": 6,
                    "name": "left_leg",
                    "position": [
                        0.13482528924942017,
                        -0.5742266178131104,
                        0.08035591244697571
                    ],
                    "rotation": [
                        0.996110737323761,
                        -0.06478025764226913,
                        -0.05569947138428688,
                        0.02158939838409424
                    ],
                    "scale": 0.7149999737739563
                },
                {
                    "children": null,
                    "flip_axis": [
                        -1.0,
                        1.0,
                        1.0
                    ],
                    "group_id": 5,
                    "name": "right_arm",
                    "position": [
                        -0.3473241329193115,
                        -0.12585115432739258,
                        0.05218243598937988
                    ],
                    "rotation": [
                        0.6950643062591553,
                        0.49344244599342346,
                        0.38209202885627747,
                        0.3569415509700775
                    ],
                    "scale": 0.675000011920929
                },
                {
                    "children": null,
                    "flip_axis": [
                        1.0,
                        1.0,
                        1.0
                    ],
                    "group_id": 5,
                    "name": "left_arm",
                    "position": [
                        0.364471435546875,
                        -0.10198688507080078,
                        0.0729876160621643
                    ],
                    "rotation": [
                        0.647618293762207,
                        0.5666029453277588,
                        -0.4314539134502411,
                        -0.2709254026412964
                    ],
                    "scale": 0.675000011920929
                }
            ],
            "flip_axis": [
                1.0,
                1.0,
                1.0
            ],
            "group_id": 4,
            "name": "tintin",
            "position": [
                -2.9741034507751465,
                0.9818363189697266,
                2.4831480979919434
            ],
            "rotation": [
                -0.2447543889284134,
                -0.01266460120677948,
                0.969089150428772,
                -0.028312206268310547
            ],
            "scale": 1.3799999952316284
        },
        {
            "children": [
                {
                    "children": null,
                    "flip_axis": [
                        -1.0,
                        1.0,
                        1.0
                    ],
                    "group_id": 6,
                    "name": "right_leg",
                    "position": [
                        -0.12999999523162842,
                        -0.550000011920929,
                        0.0
                    ],
                    "rotation": [
                        1.0,
                        0.0,
                        0.0,
                        0.0
                    ],
                    "scale": 0.7149999737739563
                },
                {
                    "children": null,
                    "flip_axis": [
                        1.0,
                        1.0,
                        1.0
                    ],
                    "group_id": 6,
                    "name": "left_leg",
                    "position": [
                        0.12999999523162842,
                        -0.550000011920929,
                        0.0
                    ],
                    "rotation": [
                        1.0,
                        0.0,
                        0.0,
                        0.0
                    ],
                    "scale": 0.7149999737739563
                },
                {
                    "children": null,
                    "flip_axis": [
                        -1.0,
                        1.0,
                        1.0
                    ],
                    "group_id": 5,
                    "name": "right_arm",
                    "position": [
                        -0.5,
                        0.11999999731779099,
                        0.0
                    ],
                    "rotation": [
                        1.0,
                        0.0,
                        0.0,
                        0.0
                    ],
                    "scale": 0.675000011920929
                },
                {
                    "children": null,
                    "flip_axis": [
                        1.0,
                        1.0,
                        1.0
                    ],
                    "group_id": 5,
                    "name": "left_arm",
                    "position": [
                        0.40422895550727844,
                        -0.054593563079833984,
                        0.12759274244308472
                    ],
                    "rotation": [
                        0.7336528301239014,
                        0.5029720664024353,
                        -0.4315703511238098,
                        -0.1500663161277771
                    ],
                    "scale": 0.675000011920929
                }
            ],
            "flip_axis": [
                1.0,
                1.0,
                1.0
            ],
            "group_id": 4,
            "name": "haddock",
            "position": [
                -51.0,
                -0.550000011920929,
                -15.0
            ],
            "rotation": [
                0.9512826204299927,
                -0.015779390931129456,
                0.30665323138237,
                0.02786026895046234
            ],
            "scale": 1.3799999952316284
        }
    ],
    "lights": [
        {
            "color": [
                1.0,
                1.0,
                1.0
            ],
            "position": [
                -95.0,
                60.0,
                -100.0
            ]
        }
    ],
    "materials": [
        {
            "color": [
                0.019999999552965164,
                0.019999999552965164,
                0.019999999552965164
            ],
            "f0": 0.20000000298023224,
            "ks": 0.30000001192092896,
            "shininess": 64.0
        },
        {
            "color": [
                0.6795181035995483,
                0.679511308670044,
                0.679511308670044
            ],
            "f0": 0.10000000149011612,
            "ks": 0.8999999761581421,
            "shininess": 128.0
        },
        {
            "color": [
                0.8999999761581421,
                0.019999999552965164,
                0.019999999552965164
            ],
            "f0": 0.019999999552965164,
            "ks": 0.10000000149011612,
            "shininess": 64.0
        },
        {
            "color": [
                0.4192771315574646,
                0.003030917141586542,
                0.003030917141586542
            ],
            "f0": 0.30000001192092896,
            "ks": 0.5,
            "shininess": 64.0
        },
        {
            "color": [
                0.0,
                0.23440024256706238,
                0.36626505851745605
            ],
            "f0": 0.30000001192092896,
            "ks": 0.5,
            "shininess": 64.0
        },
        {
            "color": [
                0.3710843324661255,
                0.371080607175827,
                0.371080607175827
            ],
            "f0": 0.20000000298023224,
            "ks": 0.5,
            "shininess": 128.0
        },
        {
            "color": [
                0.6899999976158142,
                0.6499999761581421,
                0.46000000834465027
            ],
            "f0": 0.019999999552965164,
            "ks": 0.10000000149011612,
            "shininess": 64.0
        },
        {
            "color": [
                0.5469879508018494,
                0.2214311808347702,
                0.0
            ],
            "f0": 0.019999999552965164,
            "ks": 0.10000000149011612,
            "shininess": 64.0
        }
    ]
}
